pyshiftsla/__init__.py
pyshiftsla/common_daysoff.py
pyshiftsla/daily_shifts.py
pyshiftsla/daterange.py
pyshiftsla/datetime_utilities.py
pyshiftsla/shift.py
pyshiftsla/shiftrange.py
pyshiftsla/shifts_builder.py
pyshiftsla-0.5.0.dist-info/LICENSE.md
pyshiftsla-0.5.0.dist-info/METADATA
pyshiftsla-0.5.0.dist-info/WHEEL
pyshiftsla-0.5.0.dist-info/RECORD
