Metadata-Version: 2.1
Name: pyshiftsla
Version: 0.5.0
Summary: Highly customizable SLA and work-shifts Generator, for any time-keeping and days-off policies
Author: Huy Vu Nguyen
Author-email: huyk25sinh@gmail.com
Requires-Python: >=3.10,<4.0
Classifier: Programming Language :: Python :: 3
Classifier: Programming Language :: Python :: 3.10
Classifier: Programming Language :: Python :: 3.11
Classifier: Programming Language :: Python :: 3.12
Requires-Dist: lunardate (>=0.2.2,<0.3.0)
Requires-Dist: numpy (>=1.26.2,<2.0.0)
Requires-Dist: polars (>=0.20.2,<0.21.0)
Requires-Dist: pydantic (>=2.5.2,<3.0.0)
